__init__.py
simple.py
leidian/__init__.py
leidian/api.py
leidian/executors.py
leidian/log.py
leidian/player.py
leidian/utils.py
leidian-1.0.2.dist-info/LICENSE
leidian-1.0.2.dist-info/METADATA
leidian-1.0.2.dist-info/WHEEL
leidian-1.0.2.dist-info/entry_points.txt
leidian-1.0.2.dist-info/top_level.txt
leidian-1.0.2.dist-info/RECORD
